devreminder/__init__.py
devreminder/devreminder.py
devreminder-0.0.1.dist-info/LICENSE.txt
devreminder-0.0.1.dist-info/METADATA
devreminder-0.0.1.dist-info/WHEEL
devreminder-0.0.1.dist-info/top_level.txt
devreminder-0.0.1.dist-info/RECORD
