Metadata-Version: 2.1
Name: devreminder
Version: 0.0.1
Summary: Reminder tool for developers who are engaged in fields having long execution time.
Home-page: https://github.com/cagataygulten/devreminder
Author: Çağatay Gülten
Author-email: cagataygulten@gmail.com
License: UNKNOWN
Project-URL: Bug Tracker, https://github.com/cagataygulten/devreminder/issues
Platform: UNKNOWN
Classifier: Programming Language :: Python :: 3
Classifier: License :: OSI Approved :: MIT License
Classifier: Operating System :: OS Independent
Requires-Python: >=3.6
License-File: LICENSE.txt
